rain/__init__.py
rain/_version.py
rain/loguru_logger.py
rain/core/__init__.py
rain/core/base.py
rain/core/exception.py
rain/core/execution.py
rain/core/parameter.py
rain/nodes/__init__.py
rain/nodes/custom/__init__.py
rain/nodes/custom/custom.py
rain/nodes/google_cloud_bigquery/__init__.py
rain/nodes/google_cloud_bigquery/bigquery_io.py
rain/nodes/google_cloud_storage/__init__.py
rain/nodes/google_cloud_storage/gcs_io.py
rain/nodes/mongodb/__init__.py
rain/nodes/mongodb/database_io.py
rain/nodes/pandas/__init__.py
rain/nodes/pandas/model_io.py
rain/nodes/pandas/node_structure.py
rain/nodes/pandas/pandas_io.py
rain/nodes/pandas/transform_nodes.py
rain/nodes/pandas/zscore.py
rain/nodes/pm4py/__init__.py
rain/nodes/pm4py/pm4py_conformance.py
rain/nodes/pm4py/pm4py_discovery.py
rain/nodes/pm4py/pm4py_io.py
rain/nodes/pysad/__init__.py
rain/nodes/pysad/node_structure.py
rain/nodes/pysad/trainer.py
rain/nodes/pysad/transformer.py
rain/nodes/pytorch/__init__.py
rain/nodes/pytorch/sequential.py
rain/nodes/sklearn/__init__.py
rain/nodes/sklearn/cluster.py
rain/nodes/sklearn/decomposition.py
rain/nodes/sklearn/functions.py
rain/nodes/sklearn/loaders.py
rain/nodes/sklearn/node_structure.py
rain/nodes/sklearn/svm.py
rain/nodes/spark/__init__.py
rain/nodes/spark/data_wrangling.py
rain/nodes/spark/node_structure.py
rain/nodes/spark/spark_input.py
rain/nodes/spark/spark_output.py
rain/nodes/spark/pipeline/__init__.py
rain/nodes/spark/pipeline/spark_pipeline.py
rain/nodes/spark/pipeline/stages.py
rain/nodes/tpot/__init__.py
rain/nodes/tpot/classification.py
rain/nodes/tpot/regression.py
rain_dm-1.1747167964.951835.dist-info/licenses/AUTHORS.rst
rain_dm-1.1747167964.951835.dist-info/licenses/LICENSE.md
rain_dm-1.1747167964.951835.dist-info/METADATA
rain_dm-1.1747167964.951835.dist-info/WHEEL
rain_dm-1.1747167964.951835.dist-info/top_level.txt
rain_dm-1.1747167964.951835.dist-info/RECORD
