Metadata-Version: 2.4
Name: rain-dm
Version: 1.1747167964.951835
Summary: Rain library.
Home-page: https://bitbucket.org/proslabteam/rain_unicam
Author: Università degli Studi di Camerino
License: GNU General Public License
Keywords: rain
Classifier: Development Status :: 2 - Pre-Alpha
Classifier: Intended Audience :: Developers
Classifier: Natural Language :: English
Classifier: Programming Language :: Python :: 3
Classifier: Programming Language :: Python :: 3.6
Classifier: Programming Language :: Python :: 3.7
Classifier: Programming Language :: Python :: 3.8
Requires-Python: >=3.6
License-File: LICENSE.md
License-File: AUTHORS.rst
Requires-Dist: setuptools~=57.4.0
Requires-Dist: loguru~=0.6.0
Requires-Dist: networkx~=2.7.1
Requires-Dist: pandas
Provides-Extra: full
Requires-Dist: setuptools~=57.4.0; extra == "full"
Requires-Dist: loguru~=0.6.0; extra == "full"
Requires-Dist: networkx~=2.7.1; extra == "full"
Requires-Dist: bump2version==0.5.11; extra == "full"
Requires-Dist: wheel==0.33.6; extra == "full"
Requires-Dist: watchdog==0.9.0; extra == "full"
Requires-Dist: flake8==3.7.8; extra == "full"
Requires-Dist: furo==2022.9.29; extra == "full"
Requires-Dist: tox==3.14.0; extra == "full"
Requires-Dist: coverage==6.4.4; extra == "full"
Requires-Dist: Sphinx==4.5.0; extra == "full"
Requires-Dist: twine==1.14.0; extra == "full"
Requires-Dist: pre-commit==2.13.0; extra == "full"
Requires-Dist: pytest==6.2.4; extra == "full"
Requires-Dist: pytest-cov==3.0.0; extra == "full"
Requires-Dist: pandas~=1.3.0; extra == "full"
Requires-Dist: scikit-learn~=0.24.2; extra == "full"
Requires-Dist: scikit-learn-extra~=0.3.0; extra == "full"
Requires-Dist: pm4py~=2.7.3; extra == "full"
Requires-Dist: pyspark~=3.1.2; extra == "full"
Requires-Dist: pymongo~=3.12.0; extra == "full"
Requires-Dist: numpydoc~=1.2; extra == "full"
Requires-Dist: numpy==1.22; extra == "full"
Requires-Dist: torch~=1.10.0; extra == "full"
Requires-Dist: google-cloud-storage~=1.45.0; extra == "full"
Requires-Dist: google-cloud-bigquery~=2.28.1; extra == "full"
Requires-Dist: tpot==0.11.7; extra == "full"
Requires-Dist: pysad==0.1.1; extra == "full"
Requires-Dist: combo==0.1.3; extra == "full"
Requires-Dist: mmh3==3.0.0; extra == "full"
Dynamic: author
Dynamic: classifier
Dynamic: description
Dynamic: description-content-type
Dynamic: home-page
Dynamic: keywords
Dynamic: license
Dynamic: license-file
Dynamic: provides-extra
Dynamic: requires-dist
Dynamic: requires-python
Dynamic: summary
